LICENSE
MANIFEST.in
README.rst
setup.cfg
setup.py
iwx/__init__.py
iwx/_cfg.py
iwx/containers.py
iwx/controls.py
iwx/css.py
iwx/grid.py
iwx/plot.py
iwx/utils.py
iwx.egg-info/PKG-INFO
iwx.egg-info/SOURCES.txt
iwx.egg-info/dependency_links.txt
iwx.egg-info/requires.txt
iwx.egg-info/top_level.txt
iwx/img/fig_icon.png
iwx/img/fig_icon.svg