Metadata-Version: 1.1
Name: iwx
Version: 0.1.0.dev1
Summary: wxPython utilities and enhanced controls
Home-page: https://github.com/JorgeDeLosSantos/iwx
Author: Pedro Jorge De Los Santos
Author-email: delossantosmfq@gmail.com
License: MIT
Keywords: wxPython,GUI
Platform: UNKNOWN
Classifier: Development Status :: 2 - Pre-Alpha
Classifier: Intended Audience :: Education
Classifier: Intended Audience :: Developers
Classifier: License :: OSI Approved :: MIT License
Classifier: Operating System :: OS Independent
Classifier: Programming Language :: Python
Classifier: Programming Language :: Python :: 2.7
Classifier: Programming Language :: Python :: Implementation :: CPython
Classifier: Topic :: Desktop Environment
Classifier: Topic :: Utilities
